macapptree/__init__.py
macapptree/apps.py
macapptree/exceptions.py
macapptree/extractor.py
macapptree/files.py
macapptree/launch_app.py
macapptree/main.py
macapptree/run.py
macapptree/screenshot_app_window.py
macapptree/uielement.py
macapptree/window_tools.py
macapptree-0.0.2.dist-info/METADATA
macapptree-0.0.2.dist-info/WHEEL
macapptree-0.0.2.dist-info/licenses/LICENSE
macapptree-0.0.2.dist-info/RECORD
