Metadata-Version: 2.4
Name: macapptree
Version: 0.0.2
Summary: macOS accessibility parser
Project-URL: Homepage, https://github.com/MacPaw/macapptree
Project-URL: Issues, https://github.com/MacPaw/macapptree/issues
Author-email: Maksym Shamrai <mshamrai@macpaw.com>
License-File: LICENSE
Classifier: License :: OSI Approved :: MIT License
Classifier: Operating System :: MacOS
Classifier: Programming Language :: Python :: 3
Requires-Python: >=3.8
Requires-Dist: atomacos==3.3.0
Requires-Dist: pyobjc==10.3.1
Requires-Dist: pytest==7.4.4
Requires-Dist: unidecode==1.3.8
